beanquery/__init__.py
beanquery/__main__.py
beanquery/compiler.py
beanquery/cursor.py
beanquery/cursor_test.py
beanquery/errors.py
beanquery/hashable.py
beanquery/hashable_test.py
beanquery/numberify.py
beanquery/numberify_test.py
beanquery/parser_test.py
beanquery/query.py
beanquery/query_compile.py
beanquery/query_compile_test.py
beanquery/query_env.py
beanquery/query_env_test.py
beanquery/query_execute.py
beanquery/query_execute_test.py
beanquery/query_render.py
beanquery/query_render_test.py
beanquery/query_test.py
beanquery/shell.py
beanquery/shell_test.py
beanquery/tables.py
beanquery/types.py
beanquery/types_test.py
beanquery/parser/__init__.py
beanquery/parser/ast.py
beanquery/parser/parser.py
beanquery/render/beancount.py
beanquery/render/csv.py
beanquery/render/text.py
beanquery/sources/beancount.py
beanquery/sources/csv.py
beanquery/sources/memory.py
beanquery/sources/test.py
beanquery-0.2.0.dist-info/licenses/LICENSE
docs/conf.py
beanquery-0.2.0.dist-info/METADATA
beanquery-0.2.0.dist-info/WHEEL
beanquery-0.2.0.dist-info/entry_points.txt
beanquery-0.2.0.dist-info/top_level.txt
beanquery-0.2.0.dist-info/RECORD
