Metadata-Version: 2.4
Name: beanquery
Version: 0.2.0
Summary: Customizable lightweight SQL query tool
Author-email: Martin Blais <blais@furius.ca>, Daniele Nicolodi <daniele@grinta.net>
Maintainer-email: Daniele Nicolodi <daniele@grinta.net>
License:                     GNU GENERAL PUBLIC LICENSE
Project-URL: homepage, https://github.com/beancount/beanquery
Project-URL: issues, https://github.com/beancount/beanquery/issues
Keywords: accounting,ledger,beancount,SQL,BQL
Classifier: License :: OSI Approved :: GNU General Public License v2 (GPLv2)
Classifier: Programming Language :: Python :: 3 :: Only
Classifier: Programming Language :: Python :: 3.8
Classifier: Programming Language :: Python :: 3.9
Classifier: Programming Language :: Python :: 3.10
Classifier: Programming Language :: Python :: 3.11
Classifier: Programming Language :: Python :: 3.12
Classifier: Programming Language :: Python :: 3.13
Classifier: Programming Language :: SQL
Classifier: Topic :: Office/Business :: Financial :: Accounting
Requires-Python: >=3.8
License-File: LICENSE
Requires-Dist: beancount>=2.3.4
Requires-Dist: click>7.0
Requires-Dist: python-dateutil>=2.6.0
Requires-Dist: tatsu-lts
Provides-Extra: docs
Requires-Dist: furo>=2024.08.06; extra == "docs"
Requires-Dist: sphinx~=8.1.0; extra == "docs"
Dynamic: license-file
